{
  "items": [
    {
      "title": "1km 달리기 도전, 내가 뛰겠다고 했지",
      "link": "https://blog.naver.com/kwonhuiseok/224304242333?fromRss=true&trackingCode=rss",
      "pubDate": "2026.06.03"
    },
    {
      "title": "내일부터라는 말은 오늘은 절대 안 하겠단 뜻이다",
      "link": "https://blog.naver.com/kwonhuiseok/224303172689?fromRss=true&trackingCode=rss",
      "pubDate": "2026.06.02"
    },
    {
      "title": "전학 한 번으로 다 사라진 친구들, 응답하라 1988 이 부러웠다",
      "link": "https://blog.naver.com/kwonhuiseok/224301978640?fromRss=true&trackingCode=rss",
      "pubDate": "2026.06.01"
    }
  ],
  "total": 50
}