{
  "items": [
    {
      "title": "테슬라 모델 Y 주니퍼 출고 2달째, 행복감은 여전한가",
      "link": "https://blog.naver.com/kwonhuiseok/224262966273?fromRss=true&trackingCode=rss",
      "pubDate": "2026.04.24"
    },
    {
      "title": "육아를 일처럼 느끼는 아빠, 참 싫다.",
      "link": "https://blog.naver.com/kwonhuiseok/224261720647?fromRss=true&trackingCode=rss",
      "pubDate": "2026.04.23"
    },
    {
      "title": "남자 직장 상사와 둘이서 분위기 좋은 레스토랑에 갔다.",
      "link": "https://blog.naver.com/kwonhuiseok/224260484025?fromRss=true&trackingCode=rss",
      "pubDate": "2026.04.22"
    }
  ],
  "total": 50
}