{
  "items": [
    {
      "title": "16개월 아기 미용실 가서 첫 머리 자르기, 전쟁터였다",
      "link": "https://blog.naver.com/kwonhuiseok/224308837998?fromRss=true&trackingCode=rss",
      "pubDate": "2026.06.08"
    },
    {
      "title": "글쓰기 커뮤니티 규칙 변경, 내 욕심이었다",
      "link": "https://blog.naver.com/kwonhuiseok/224308056057?fromRss=true&trackingCode=rss",
      "pubDate": "2026.06.07"
    },
    {
      "title": "대한민국에 진짜 보수는 없다",
      "link": "https://blog.naver.com/kwonhuiseok/224307299460?fromRss=true&trackingCode=rss",
      "pubDate": "2026.06.06"
    }
  ],
  "total": 50
}